{
  "levelId": "level_011",
  "difficulty": "hard",
  "gridSize": 6,
  "exit": {
    "row": 1,
    "col": 5,
    "orientation": "horizontal"
  },
  "targetCar": {
    "id": "T",
    "row": 1,
    "col": 0,
    "length": 2,
    "orientation": "horizontal"
  },
  "blockingCars": [
    {
      "id": "A",
      "row": 2,
      "col": 1,
      "length": 2,
      "orientation": "vertical"
    },
    {
      "id": "B",
      "row": 4,
      "col": 1,
      "length": 2,
      "orientation": "horizontal"
    },
    {
      "id": "C",
      "row": 0,
      "col": 2,
      "length": 2,
      "orientation": "vertical"
    },
    {
      "id": "D",
      "row": 2,
      "col": 2,
      "length": 2,
      "orientation": "horizontal"
    },
    {
      "id": "E",
      "row": 0,
      "col": 3,
      "length": 2,
      "orientation": "vertical"
    },
    {
      "id": "F",
      "row": 0,
      "col": 4,
      "length": 2,
      "orientation": "vertical"
    },
    {
      "id": "G",
      "row": 2,
      "col": 4,
      "length": 2,
      "orientation": "horizontal"
    },
    {
      "id": "H",
      "row": 3,
      "col": 0,
      "length": 3,
      "orientation": "vertical"
    },
    {
      "id": "I",
      "row": 3,
      "col": 3,
      "length": 3,
      "orientation": "horizontal"
    }
  ]
}